hilogenerator/__init__.py
sqlalchemy_hilo-0.1.2.dist-info/DESCRIPTION.rst
sqlalchemy_hilo-0.1.2.dist-info/METADATA
sqlalchemy_hilo-0.1.2.dist-info/RECORD
sqlalchemy_hilo-0.1.2.dist-info/WHEEL
sqlalchemy_hilo-0.1.2.dist-info/metadata.json
sqlalchemy_hilo-0.1.2.dist-info/top_level.txt
