Metadata-Version: 2.0
Name: sqlalchemy-hilo
Version: 0.1.2
Summary: HiLo primary key generators for sqlalchemy
Home-page: https://github.com/shosca/sqlalchemy-hilo
Author: UNKNOWN
Author-email: UNKNOWN
License: MIT
Keywords: generator hilo sql sqlalchemy
Platform: UNKNOWN
Classifier: Intended Audience :: Developers
Classifier: Natural Language :: English
Classifier: Programming Language :: Python
Classifier: Programming Language :: Python :: 2.7
Classifier: Programming Language :: Python :: 3
Classifier: Development Status :: 2 - Pre-Alpha
Requires-Dist: six
Requires-Dist: SQLAlchemy
Requires-Dist: setuptools
